tox_console_scripts/__init__.py
tox_console_scripts/plugin.py
tox_console_scripts/version.py
tox_console_scripts-0.4.0.dist-info/LICENSE
tox_console_scripts-0.4.0.dist-info/METADATA
tox_console_scripts-0.4.0.dist-info/WHEEL
tox_console_scripts-0.4.0.dist-info/entry_points.txt
tox_console_scripts-0.4.0.dist-info/top_level.txt
tox_console_scripts-0.4.0.dist-info/RECORD
