Metadata-Version: 2.2
Name: tox-console-scripts
Version: 0.4.0
Summary: Create console scripts of system site packages within tox env
Author: Stanislav Levin
Maintainer: Stanislav Levin
License: MIT License
Project-URL: Homepage, https://github.com/stanislavlevin/tox-console-scripts
Project-URL: Repository, https://github.com/stanislavlevin/tox-console-scripts
Project-URL: Issues, https://github.com/stanislavlevin/tox-console-scripts/issues
Keywords: virtual,environments,isolated,testing
Classifier: Development Status :: 4 - Beta
Classifier: Framework :: tox
Classifier: Intended Audience :: Developers
Classifier: License :: OSI Approved :: MIT License
Classifier: Operating System :: Unix
Classifier: Topic :: Software Development :: Testing
Classifier: Topic :: Software Development :: Libraries
Classifier: Topic :: Utilities
Classifier: Programming Language :: Python :: 3
Classifier: Programming Language :: Python :: 3 :: Only
Classifier: Programming Language :: Python :: 3.9
Classifier: Programming Language :: Python :: 3.10
Classifier: Programming Language :: Python :: 3.11
Classifier: Programming Language :: Python :: 3.12
Classifier: Programming Language :: Python :: 3.13
Requires-Python: >=3.9
License-File: LICENSE
Requires-Dist: tox>4
Requires-Dist: pyproject-installer>=0.4.0
